xtuples/__about__.py
xtuples/__init__.py
xtuples/f.py
xtuples/i.py
xtuples/n.py
xtuples-3.1.0.dist-info/METADATA
xtuples-3.1.0.dist-info/WHEEL
xtuples-3.1.0.dist-info/licenses/LICENSE
xtuples-3.1.0.dist-info/licenses/LICENSE.txt
xtuples-3.1.0.dist-info/RECORD
