Metadata-Version: 2.1
Name: xtuples
Version: 3.1.0
Project-URL: Documentation, https://github.com/tomjrwilliams/xtuples
Project-URL: Issues, https://github.com/tomjrwilliams/xtuples/issues
Project-URL: Source, https://github.com/tomjrwilliams/xtuples
Author-email: Tom Williams <tomjrw@gmail.com>
License-Expression: MIT
License-File: LICENSE
License-File: LICENSE.txt
Classifier: Development Status :: 4 - Beta
Classifier: Programming Language :: Python
Classifier: Programming Language :: Python :: 3.9
Classifier: Programming Language :: Python :: 3.10
Classifier: Programming Language :: Python :: 3.11
Classifier: Programming Language :: Python :: Implementation :: CPython
Classifier: Programming Language :: Python :: Implementation :: PyPy
Requires-Python: <=3.11,>=3.9
